promisegraph/__init__.py
promisegraph-0.0.1.dist-info/LICENSE
promisegraph-0.0.1.dist-info/METADATA
promisegraph-0.0.1.dist-info/WHEEL
promisegraph-0.0.1.dist-info/RECORD
