Metadata-Version: 2.1
Name: promisegraph
Version: 0.0.1
Summary: TODO Oleksandr
License: MIT
Author: Oleksandr Tereshchenko
Author-email: toporok@gmail.com
Requires-Python: >=3.9,<4.0
Classifier: License :: OSI Approved :: MIT License
Classifier: Programming Language :: Python :: 3
Classifier: Programming Language :: Python :: 3.9
Classifier: Programming Language :: Python :: 3.10
Classifier: Programming Language :: Python :: 3.11
Classifier: Programming Language :: Python :: 3.12
Requires-Dist: pydantic (>=2.0.0,<3.0.0)
